pydango/__init__.py
pydango/__main__.py
pydango/cinephile.py
pydango/cinephile_sqlite.py
pydango/connection.py
pydango/dbconfig.py
pydango/init_data.py
pydango/primary_func.py
pydango/secondary_func.py
pydango/state.py
pydango/switchlang.py
pydango/tables.py
pydango/theater_owner.py
pydango/theater_owner_sqlite.py
pydango-1.0.0.dist-info/LICENSE
pydango-1.0.0.dist-info/METADATA
pydango-1.0.0.dist-info/WHEEL
pydango-1.0.0.dist-info/entry_points.txt
pydango-1.0.0.dist-info/top_level.txt
pydango-1.0.0.dist-info/RECORD
