Metadata-Version: 2.1
Name: pydango
Version: 1.0.0
Summary: Pip installable database schema that attempts to mimic the Fandango database
Home-page: https://github.com/Captmoonshot/pydango
Author: Sammy Lee
Author-email: sam@gygantor.com
License: MIT
Platform: UNKNOWN
Classifier: License :: OSI Approved :: MIT License
Classifier: Programming Language :: Python :: 3
Classifier: Programming Language :: Python :: 3.8
Requires-Dist: sqlalchemy (==1.3.22)
Requires-Dist: sqlalchemy-utils (==0.36.8)
Requires-Dist: psycopg2-binary (==2.8.6)
Requires-Dist: passlib (==1.7.4)
Requires-Dist: python-dateutil (==2.8.1)
